{
  "posts": [
    {
      "id": "1",
      "title": "json-server",
      "author": "typicode"
    }
  ],
  "comments": [
    {
      "id": "1",
      "body": "some comment",
      "postId": "1"
    }
  ],
  "users": [
    {
      "id": "1",
      "username": "admin",
      "password": "123"
    }
  ],
  "profile": {
    "first": "Ян",
    "lastname": "Неровный",
    "age": 54545,
    "currency": "EUR",
    "country": "Ukraine",
    "city": "Istanbul",
    "username": "admin",
    "avatar": "https://encrypted-tbn0.gstatic.com/images?q=tbn:ANd9GcTyz-77X11MoGE22xVjjPhbpW6lPj6I0SkcTQ&usqp=CAU"
  }
}